RobotFramework_UDS/DiagnosticServices.py
RobotFramework_UDS/RobotFramework_UDS.pdf
RobotFramework_UDS/UDSKeywords.py
RobotFramework_UDS/__init__.py
RobotFramework_UDS/version.py
RobotFramework_UDS-0.1.17.dist-info/LICENSE
RobotFramework_UDS-0.1.17.dist-info/METADATA
RobotFramework_UDS-0.1.17.dist-info/WHEEL
RobotFramework_UDS-0.1.17.dist-info/top_level.txt
RobotFramework_UDS-0.1.17.dist-info/RECORD
