Metadata-Version: 2.1
Name: RobotFramework-UDS
Version: 0.1.17
Summary: Robot Framework keywords for UDS (Unified Diagnostic Services) communication
Home-page: https://github.com/test-fullautomation/robotframework-uds
Author: Mai Minh Tri
Author-email: tri.maiMinh@vn.bosch.com
License: UNKNOWN
Platform: UNKNOWN
Classifier: Programming Language :: Python :: 3
Classifier: License :: OSI Approved :: Apache Software License
Classifier: Operating System :: OS Independent
Classifier: Development Status :: 4 - Beta
Classifier: Intended Audience :: Developers
Classifier: Topic :: Software Development
Requires-Python: >=3.0
License-File: LICENSE
Requires-Dist: robotframework
Requires-Dist: udsoncan
Requires-Dist: doipclient
Requires-Dist: odxtools
